inputflow/__init__.py
inputflow/admin.py
inputflow/apps.py
inputflow/models.py
inputflow/urls.py
inputflow/utils.py
inputflow/views.py
inputflow/migrations/0001_initial.py
inputflow/migrations/0002_webhook.py
inputflow/migrations/0003_auto_20191011_0015.py
inputflow/migrations/0004_auto_20200225_2042.py
inputflow/migrations/0005_auto_20211014_2145.py
inputflow/migrations/__init__.py
inputflow/static/css/inputflow.css
inputflow/static/js/inputflow.js
inputflow/templates/inputflow/base.html
dj_input_flow-0.1.9.dist-info/AUTHORS.rst
dj_input_flow-0.1.9.dist-info/LICENSE
dj_input_flow-0.1.9.dist-info/METADATA
dj_input_flow-0.1.9.dist-info/WHEEL
dj_input_flow-0.1.9.dist-info/top_level.txt
dj_input_flow-0.1.9.dist-info/RECORD
