Metadata-Version: 2.1
Name: dj-input-flow
Version: 0.1.9
Summary: Django app to handle data flow
Home-page: https://github.com/kverdecia/dj-input-flow
Author: Karel Antonio Verdecia Ortiz
Author-email: kverdecia@gmail.com
License: MIT
Keywords: dj-input-flow
Platform: UNKNOWN
Classifier: Development Status :: 3 - Alpha
Classifier: Framework :: Django :: 1.11
Classifier: Framework :: Django :: 2.0
Classifier: Intended Audience :: Developers
Classifier: License :: OSI Approved :: BSD License
Classifier: Natural Language :: English
Classifier: Programming Language :: Python :: 2
Classifier: Programming Language :: Python :: 2.7
Classifier: Programming Language :: Python :: 3
Classifier: Programming Language :: Python :: 3.4
Classifier: Programming Language :: Python :: 3.5
Classifier: Programming Language :: Python :: 3.6
License-File: LICENSE
License-File: AUTHORS.rst
